dmk_packages/__init__.py
dmk_packages/naver_datalab.py
dmk_packages/crawler/__init__.py
dmk_packages/crawler/bigkinds.py
dmk_packages/crawler/clien.py
dmk_packages/crawler/fnguide.py
dmk_packages/crawler/naver_blog.py
dmk_packages/crawler/naver_search_volume.py
dmk_packages/crawler/youtube.py
dmk_packages/database/__init__.py
dmk_packages/database/database.py
dmk_packages/utils/__init__.py
dmk_packages/utils/day_off.py
dmk_packages/utils/pdf_to_text.py
dmk_packages-0.7.6.dist-info/LICENSE
dmk_packages-0.7.6.dist-info/METADATA
dmk_packages-0.7.6.dist-info/WHEEL
dmk_packages-0.7.6.dist-info/top_level.txt
dmk_packages-0.7.6.dist-info/RECORD
