Metadata-Version: 2.1
Name: dmk_packages
Version: 0.7.6
Summary: Common packages for DataMKTKorea
Author-email: DataMarketingKorea <infra@datamarketing.co.kr>
Classifier: Programming Language :: Python :: 3
Classifier: License :: OSI Approved :: Apache Software License
Classifier: Operating System :: OS Independent
Requires-Python: >=3.9
License-File: LICENSE
Requires-Dist: SQLAlchemy
Requires-Dist: python-dotenv
Requires-Dist: psycopg2-binary
